<?xml version="1.0" encoding="UTF-8"?><record_update table="sys_atf_step">
    <sys_atf_step action="DELETE">
        <active>true</active>
        <copied_from display_value="">7f403e8a1b5050d0a89720a8ec4bcbdb</copied_from>
        <description>Run Server Side Validation Script</description>
        <display_name>Run Server Side Script</display_name>
        <inputs/>
        <mugshots_cache_json/>
        <notes>Verify that the users, groups and silos have been set up properly</notes>
        <order>8</order>
        <snapshot/>
        <step_config display_value="Run Server Side Script">41de4a935332120028bc29cac2dc349a</step_config>
        <sys_class_name>sys_atf_step</sys_class_name>
        <sys_created_by>admin</sys_created_by>
        <sys_created_on>2020-05-15 14:24:49</sys_created_on>
        <sys_id>6866b1a11bfc5810a89720a8ec4bcb70</sys_id>
        <sys_mod_count>15</sys_mod_count>
        <sys_name>Run Server Side Script</sys_name>
        <sys_package display_value="DataSilos" source="x_snc_datasilos">dafbffebdbb78450ba15a353059619eb</sys_package>
        <sys_policy/>
        <sys_scope display_value="DataSilos">dafbffebdbb78450ba15a353059619eb</sys_scope>
        <sys_update_name>sys_atf_step_6866b1a11bfc5810a89720a8ec4bcb70</sys_update_name>
        <sys_updated_by>admin</sys_updated_by>
        <sys_updated_on>2020-05-15 14:48:23</sys_updated_on>
        <table/>
        <test display_value="">086671a11bfc5810a89720a8ec4bcbea</test>
        <timeout/>
        <warning_message/>
    </sys_atf_step>
    <sys_variable_value action="DELETE" query="document_key=6866b1a11bfc5810a89720a8ec4bcb70"/>
    <sys_variable_value action="DELETE">
        <document>sys_atf_step</document>
        <document_key>6866b1a11bfc5810a89720a8ec4bcb70</document_key>
        <order>200</order>
        <sys_class_name>sys_variable_value</sys_class_name>
        <sys_created_by>admin</sys_created_by>
        <sys_created_on>2020-05-15 14:24:49</sys_created_on>
        <sys_id>2866b1a11bfc5810a89720a8ec4bcb71</sys_id>
        <sys_mod_count>1</sys_mod_count>
        <sys_updated_by>admin</sys_updated_by>
        <sys_updated_on>2020-05-15 14:24:49</sys_updated_on>
        <value>(function(outputs, steps, stepResult, assertEqual) {&#13;
&#13;
	&#13;
	&#13;
	var RenderValue = x_snc_devtools.RenderValue;&#13;
	var Debug = x_snc_devtools.Debug;&#13;
	var GetGroupsFromUser = x_snc_devtools.GetGroupsFromUser;&#13;
&#13;
	Debug('Verify the creation of users during the InitializeRecords test');&#13;
	&#13;
	stepUserA_MEMBER = steps('1066b1a11bfc5810a89720a8ec4bcb3f');&#13;
	stepUserA_FULFILLER = steps('dc66b1a11bfc5810a89720a8ec4bcb4f');&#13;
	stepUserA_SUPERVISOR = steps('2866b1a11bfc5810a89720a8ec4bcb60');&#13;
&#13;
	&#13;
	var strUserA_MEMBER = stepUserA_MEMBER.user.toString();&#13;
	var strUserA_FULFILLER = stepUserA_FULFILLER.user.toString();&#13;
	var strUserA_SUPERVISOR = stepUserA_SUPERVISOR.user.toString();&#13;
&#13;
	&#13;
	Debug('User A-MEMBER: '+strUserA_MEMBER);&#13;
	Debug('User A-FULFILLER: '+strUserA_FULFILLER);&#13;
	Debug('User A-SUPERVISOR: '+strUserA_SUPERVISOR);&#13;
	&#13;
&#13;
	var aUserA_MEMBERGroups = GetGroupsFromUser(strUserA_MEMBER);&#13;
	var aUserA_FULFILLERGroups = GetGroupsFromUser(strUserA_FULFILLER);&#13;
	var aUserA_SUPERVISORGroups = GetGroupsFromUser(strUserA_SUPERVISOR);&#13;
	&#13;
	Debug('Groups A-MEMBER: '+RenderValue(aUserA_MEMBERGroups));&#13;
	Debug('Groups A-FULFILLER: '+RenderValue(aUserA_FULFILLERGroups));&#13;
	Debug('Groups A-SUPERVISOR: '+RenderValue(aUserA_SUPERVISORGroups));&#13;
	&#13;
	if (aUserA_MEMBERGroups.length == 0)&#13;
	{&#13;
		Debug('Error: A-MEMBER has no groups!');&#13;
		return false;&#13;
	}&#13;
	if (aUserA_FULFILLERGroups.length == 0)&#13;
	{&#13;
		Debug('Error: A-FULFILLER has no groups!');&#13;
&#13;
		return false;&#13;
	}&#13;
	&#13;
	var aUserA_MEMBERSilos = GetSilosFromUser(strUserA_MEMBER);&#13;
	var aUserA_FULFILLERSilos = GetSilosFromUser(strUserA_FULFILLER);&#13;
&#13;
	Debug('Silos A-MEMBER: '+RenderValue(aUserA_MEMBERSilos));&#13;
	Debug('Silos A-FULFILLER: '+RenderValue(aUserA_FULFILLERSilos));&#13;
	&#13;
	if (aUserA_MEMBERSilos.length == 0)&#13;
	{&#13;
		Debug('Error: User A-MEMBER has no silos!');&#13;
		return false;&#13;
	}&#13;
	if (aUserA_FULFILLERSilos.length == 0)&#13;
	{&#13;
		Debug('Error: User A-FULFILLER has no silos!');&#13;
		return false;&#13;
	}&#13;
&#13;
	&#13;
	&#13;
})(outputs, steps, stepResult, assertEqual);&#13;
</value>
        <variable display_value="">989d9e235324220002c6435723dc3484</variable>
    </sys_variable_value>
    <sys_variable_value action="DELETE">
        <document>sys_atf_step</document>
        <document_key>6866b1a11bfc5810a89720a8ec4bcb70</document_key>
        <order>100</order>
        <sys_class_name>sys_variable_value</sys_class_name>
        <sys_created_by>admin</sys_created_by>
        <sys_created_on>2020-05-15 14:24:49</sys_created_on>
        <sys_id>6466b1a11bfc5810a89720a8ec4bcb71</sys_id>
        <sys_mod_count>0</sys_mod_count>
        <sys_updated_by>admin</sys_updated_by>
        <sys_updated_on>2020-05-15 14:24:49</sys_updated_on>
        <value>3.1</value>
        <variable display_value="">42f2564b73031300440211d8faf6a777</variable>
    </sys_variable_value>
    <sys_update_version action="INSERT_OR_UPDATE">
        <action>DELETE</action>
        <application display_value="DataSilos">dafbffebdbb78450ba15a353059619eb</application>
        <file_path/>
        <instance_id>8bbd52e6db1a8cd02f68c59705961990</instance_id>
        <instance_name>empswildgrube1</instance_name>
        <name>sys_atf_step_6866b1a11bfc5810a89720a8ec4bcb70</name>
        <payload><![CDATA[<?xml version="1.0" encoding="UTF-8"?><record_update table="sys_atf_step"><sys_atf_step action="INSERT_OR_UPDATE"><active>true</active><copied_from display_value="">7f403e8a1b5050d0a89720a8ec4bcbdb</copied_from><description>Run Server Side Validation Script</description><display_name>Run Server Side Script</display_name><inputs/><mugshots_cache_json/><notes>Verify that the users, groups and silos have been set up properly</notes><order>8</order><snapshot/><step_config display_value="Run Server Side Script">41de4a935332120028bc29cac2dc349a</step_config><sys_class_name>sys_atf_step</sys_class_name><sys_created_by>admin</sys_created_by><sys_created_on>2020-05-15 14:24:49</sys_created_on><sys_id>6866b1a11bfc5810a89720a8ec4bcb70</sys_id><sys_mod_count>15</sys_mod_count><sys_name>Run Server Side Script</sys_name><sys_package display_value="DataSilos" source="x_snc_datasilos">dafbffebdbb78450ba15a353059619eb</sys_package><sys_policy/><sys_scope display_value="DataSilos">dafbffebdbb78450ba15a353059619eb</sys_scope><sys_update_name>sys_atf_step_6866b1a11bfc5810a89720a8ec4bcb70</sys_update_name><sys_updated_by>admin</sys_updated_by><sys_updated_on>2020-05-15 14:48:23</sys_updated_on><table/><test display_value="">086671a11bfc5810a89720a8ec4bcbea</test><timeout/><warning_message/></sys_atf_step><sys_variable_value action="delete_multiple" query="document_key=6866b1a11bfc5810a89720a8ec4bcb70"/><sys_variable_value action="INSERT_OR_UPDATE"><document>sys_atf_step</document><document_key>6866b1a11bfc5810a89720a8ec4bcb70</document_key><order>200</order><sys_class_name>sys_variable_value</sys_class_name><sys_created_by>admin</sys_created_by><sys_created_on>2020-05-15 14:24:49</sys_created_on><sys_id>2866b1a11bfc5810a89720a8ec4bcb71</sys_id><sys_mod_count>1</sys_mod_count><sys_updated_by>admin</sys_updated_by><sys_updated_on>2020-05-15 14:24:49</sys_updated_on><value>(function(outputs, steps, stepResult, assertEqual) {&#13;
&#13;
	&#13;
	&#13;
	var RenderValue = x_snc_devtools.RenderValue;&#13;
	var Debug = x_snc_devtools.Debug;&#13;
	var GetGroupsFromUser = x_snc_devtools.GetGroupsFromUser;&#13;
&#13;
	Debug('Verify the creation of users during the InitializeRecords test');&#13;
	&#13;
	stepUserA_MEMBER = steps('1066b1a11bfc5810a89720a8ec4bcb3f');&#13;
	stepUserA_FULFILLER = steps('dc66b1a11bfc5810a89720a8ec4bcb4f');&#13;
	stepUserA_SUPERVISOR = steps('2866b1a11bfc5810a89720a8ec4bcb60');&#13;
&#13;
	&#13;
	var strUserA_MEMBER = stepUserA_MEMBER.user.toString();&#13;
	var strUserA_FULFILLER = stepUserA_FULFILLER.user.toString();&#13;
	var strUserA_SUPERVISOR = stepUserA_SUPERVISOR.user.toString();&#13;
&#13;
	&#13;
	Debug('User A-MEMBER: '+strUserA_MEMBER);&#13;
	Debug('User A-FULFILLER: '+strUserA_FULFILLER);&#13;
	Debug('User A-SUPERVISOR: '+strUserA_SUPERVISOR);&#13;
	&#13;
&#13;
	var aUserA_MEMBERGroups = GetGroupsFromUser(strUserA_MEMBER);&#13;
	var aUserA_FULFILLERGroups = GetGroupsFromUser(strUserA_FULFILLER);&#13;
	var aUserA_SUPERVISORGroups = GetGroupsFromUser(strUserA_SUPERVISOR);&#13;
	&#13;
	Debug('Groups A-MEMBER: '+RenderValue(aUserA_MEMBERGroups));&#13;
	Debug('Groups A-FULFILLER: '+RenderValue(aUserA_FULFILLERGroups));&#13;
	Debug('Groups A-SUPERVISOR: '+RenderValue(aUserA_SUPERVISORGroups));&#13;
	&#13;
	if (aUserA_MEMBERGroups.length == 0)&#13;
	{&#13;
		Debug('Error: A-MEMBER has no groups!');&#13;
		return false;&#13;
	}&#13;
	if (aUserA_FULFILLERGroups.length == 0)&#13;
	{&#13;
		Debug('Error: A-FULFILLER has no groups!');&#13;
&#13;
		return false;&#13;
	}&#13;
	&#13;
	var aUserA_MEMBERSilos = GetSilosFromUser(strUserA_MEMBER);&#13;
	var aUserA_FULFILLERSilos = GetSilosFromUser(strUserA_FULFILLER);&#13;
&#13;
	Debug('Silos A-MEMBER: '+RenderValue(aUserA_MEMBERSilos));&#13;
	Debug('Silos A-FULFILLER: '+RenderValue(aUserA_FULFILLERSilos));&#13;
	&#13;
	if (aUserA_MEMBERSilos.length == 0)&#13;
	{&#13;
		Debug('Error: User A-MEMBER has no silos!');&#13;
		return false;&#13;
	}&#13;
	if (aUserA_FULFILLERSilos.length == 0)&#13;
	{&#13;
		Debug('Error: User A-FULFILLER has no silos!');&#13;
		return false;&#13;
	}&#13;
&#13;
	&#13;
	&#13;
})(outputs, steps, stepResult, assertEqual);&#13;
</value><variable display_value="">989d9e235324220002c6435723dc3484</variable></sys_variable_value><sys_variable_value action="INSERT_OR_UPDATE"><document>sys_atf_step</document><document_key>6866b1a11bfc5810a89720a8ec4bcb70</document_key><order>100</order><sys_class_name>sys_variable_value</sys_class_name><sys_created_by>admin</sys_created_by><sys_created_on>2020-05-15 14:24:49</sys_created_on><sys_id>6466b1a11bfc5810a89720a8ec4bcb71</sys_id><sys_mod_count>0</sys_mod_count><sys_updated_by>admin</sys_updated_by><sys_updated_on>2020-05-15 14:24:49</sys_updated_on><value>3.1</value><variable display_value="">42f2564b73031300440211d8faf6a777</variable></sys_variable_value></record_update>]]></payload>
        <payload_hash>-898383618</payload_hash>
        <record_name>Run Server Side Script</record_name>
        <reverted_from/>
        <source>627c4948db2c1410ba15a35305961906</source>
        <source_table>sys_update_set</source_table>
        <state>previous</state>
        <sys_created_by>admin</sys_created_by>
        <sys_created_on>2020-05-15 14:48:23</sys_created_on>
        <sys_id>b5cb75691bfc5810a89720a8ec4bcb0f</sys_id>
        <sys_mod_count>0</sys_mod_count>
        <sys_recorded_at>17218cec5500000001</sys_recorded_at>
        <sys_updated_by>admin</sys_updated_by>
        <sys_updated_on>2020-05-15 14:48:23</sys_updated_on>
        <type>Test Step</type>
        <update_guid>fdcb756963fc58103d3dba929e34600e</update_guid>
        <update_guid_history>fdcb756963fc58103d3dba929e34600e:-898383618,34cb35692bfc5810ec5de0684e35810d:1938524991,b3bbf169c9fc58107135945627dbc65b:-1832913701,99bb316969fc581029dbcafe9241bbf9:1003994908,17abbd293afc5810cfb43f3d67fe85fa:-454063779,0aabbd29bdfc5810a07f38aef891bc07:-1912122466,bcab3d29b6fc5810d70e89e5610446c1:924786143,a866b1a134fc58106538da4995b2e28f:1530261180,6c66b1a171fc58102ef95e27f83f7a8b:-1111306430</update_guid_history>
    </sys_update_version>
    <sys_metadata_delete action="INSERT_OR_UPDATE">
        <sys_audit_delete/>
        <sys_class_name>sys_metadata_delete</sys_class_name>
        <sys_created_by>admin</sys_created_by>
        <sys_created_on>2020-05-15 14:48:25</sys_created_on>
        <sys_db_object display_value="" name="sys_atf_step">sys_atf_step</sys_db_object>
        <sys_id>56bc7a82cab04e2196210778c231cc99</sys_id>
        <sys_metadata>6866b1a11bfc5810a89720a8ec4bcb70</sys_metadata>
        <sys_mod_count>0</sys_mod_count>
        <sys_name>Run Server Side Script</sys_name>
        <sys_package display_value="DataSilos" source="x_snc_datasilos">dafbffebdbb78450ba15a353059619eb</sys_package>
        <sys_parent/>
        <sys_policy/>
        <sys_scope display_value="DataSilos">dafbffebdbb78450ba15a353059619eb</sys_scope>
        <sys_scope_delete display_value="">13d28564f033417896743d5e7fb82131</sys_scope_delete>
        <sys_update_name>sys_atf_step_6866b1a11bfc5810a89720a8ec4bcb70</sys_update_name>
        <sys_update_version display_value="sys_atf_step_6866b1a11bfc5810a89720a8ec4bcb70">b5cb75691bfc5810a89720a8ec4bcb0f</sys_update_version>
        <sys_updated_by>admin</sys_updated_by>
        <sys_updated_on>2020-05-15 14:48:25</sys_updated_on>
    </sys_metadata_delete>
</record_update>
